my_component/__init__.py
my_component/example.py
my_component/frontend/build/asset-manifest.json
my_component/frontend/build/bootstrap.min.css
my_component/frontend/build/index.html
my_component/frontend/build/static/css/main.98efc5e3.css
my_component/frontend/build/static/css/main.98efc5e3.css.map
my_component/frontend/build/static/js/main.422d4635.js
my_component/frontend/build/static/js/main.422d4635.js.LICENSE.txt
my_component/frontend/build/static/js/main.422d4635.js.map
streamlit_interactive_gantt_job_shop/__init__.py
streamlit_interactive_gantt_job_shop/example.py
streamlit_interactive_gantt_job_shop/frontend/build/asset-manifest.json
streamlit_interactive_gantt_job_shop/frontend/build/bootstrap.min.css
streamlit_interactive_gantt_job_shop/frontend/build/index.html
streamlit_interactive_gantt_job_shop/frontend/build/static/css/main.98efc5e3.css
streamlit_interactive_gantt_job_shop/frontend/build/static/css/main.98efc5e3.css.map
streamlit_interactive_gantt_job_shop/frontend/build/static/js/main.422d4635.js
streamlit_interactive_gantt_job_shop/frontend/build/static/js/main.422d4635.js.LICENSE.txt
streamlit_interactive_gantt_job_shop/frontend/build/static/js/main.422d4635.js.map
streamlit_interactive_gantt_job_shop-0.0.6.dist-info/LICENSE
streamlit_interactive_gantt_job_shop-0.0.6.dist-info/METADATA
streamlit_interactive_gantt_job_shop-0.0.6.dist-info/WHEEL
streamlit_interactive_gantt_job_shop-0.0.6.dist-info/top_level.txt
streamlit_interactive_gantt_job_shop-0.0.6.dist-info/RECORD
